EasyPygame/actors.py
EasyPygame/game_engine.py
EasyPygame/input_controller.py
EzPygame/actors.py
EzPygame/game_engine.py
EzPygame/input_controller.py
EasyPygame-0.1.1.dist-info/METADATA
EasyPygame-0.1.1.dist-info/WHEEL
EasyPygame-0.1.1.dist-info/top_level.txt
EasyPygame-0.1.1.dist-info/zip-safe
EasyPygame-0.1.1.dist-info/RECORD
