Metadata-Version: 2.1
Name: EasyPygame
Version: 0.1.1
Summary: A plugin to make Pygame easy!
Home-page: https://github.com/RyanKeys/EzPygame
Author: Ryan Keys
Author-email: r.keys1998@gmail.com
License: MIT
Platform: UNKNOWN
